[
    {
        "type": "Armor",
        "classes": [
            {
                "url": "/api/classes/1",
                "name": "Barbarian"
            },
            {
                "url": "/api/classes/2",
                "name": "Bard"
            },
            {
                "url": "/api/classes/3",
                "name": "Cleric"
            },
            {
                "url": "/api/classes/4",
                "name": "Druid"
            },
            {
                "url": "/api/classes/8",
                "name": "Ranger"
            },
            {
                "url": "/api/classes/9",
                "name": "Rogue"
            },
            {
                "url": "/api/classes/11",
                "name": "Warlock"
            }
        ],
        "races": [],
        "entry_descriptor": {
            "index": 1,
            "url": "/api/proficiencies/1",
            "name": "Light armor",
            "desc": []
        }
    },
    {
        "type": "Armor",
        "classes": [
            {
                "url": "/api/classes/1",
                "name": "Barbarian"
            },
            {
                "url": "/api/classes/3",
                "name": "Cleric"
            },
            {
                "url": "/api/classes/4",
                "name": "Druid"
            },
            {
                "url": "/api/classes/8",
                "name": "Ranger"
            }
        ],
        "races": [],
        "entry_descriptor": {
            "index": 2,
            "url": "/api/proficiencies/2",
            "name": "Medium armor",
            "desc": []
        }
    },
    {
        "type": "Armor",
        "classes": [],
        "races": [],
        "entry_descriptor": {
            "index": 3,
            "url": "/api/proficiencies/3",
            "name": "Heavy armor",
            "desc": []
        }
    },
    {
        "type": "Armor",
        "classes": [
            {
                "url": "/api/classes/5",
                "name": "Fighter"
            },
            {
                "url": "/api/classes/7",
                "name": "Paladin"
            }
        ],
        "races": [],
        "entry_descriptor": {
            "index": 4,
            "url": "/api/proficiencies/4",
            "name": "All armor",
            "desc": []
        }
    },
    {
        "type": "Armor",
        "classes": [],
        "races": [],
        "entry_descriptor": {
            "index": 5,
            "url": "/api/proficiencies/5",
            "name": "Padded",
            "desc": []
        }
    },
    {
        "type": "Armor",
        "classes": [],
        "races": [],
        "entry_descriptor": {
            "index": 6,
            "url": "/api/proficiencies/6",
            "name": "Leather",
            "desc": []
        }
    },
    {
        "type": "Armor",
        "classes": [],
        "races": [],
        "entry_descriptor": {
            "index": 7,
            "url": "/api/proficiencies/7",
            "name": "Studded Leather",
            "desc": []
        }
    },
    {
        "type": "Armor",
        "classes": [],
        "races": [],
        "entry_descriptor": {
            "index": 8,
            "url": "/api/proficiencies/8",
            "name": "Hide",
            "desc": []
        }
    },
    {
        "type": "Armor",
        "classes": [],
        "races": [],
        "entry_descriptor": {
            "index": 9,
            "url": "/api/proficiencies/9",
            "name": "Chain Shirt",
            "desc": []
        }
    },
    {
        "type": "Armor",
        "classes": [],
        "races": [],
        "entry_descriptor": {
            "index": 10,
            "url": "/api/proficiencies/10",
            "name": "Scale Mail",
            "desc": []
        }
    },
    {
        "type": "Armor",
        "classes": [],
        "races": [],
        "entry_descriptor": {
            "index": 11,
            "url": "/api/proficiencies/11",
            "name": "Breastplate",
            "desc": []
        }
    },
    {
        "type": "Armor",
        "classes": [],
        "races": [],
        "entry_descriptor": {
            "index": 12,
            "url": "/api/proficiencies/12",
            "name": "Half Plate",
            "desc": []
        }
    },
    {
        "type": "Armor",
        "classes": [],
        "races": [],
        "entry_descriptor": {
            "index": 13,
            "url": "/api/proficiencies/13",
            "name": "Ring Mail",
            "desc": []
        }
    },
    {
        "type": "Armor",
        "classes": [],
        "races": [],
        "entry_descriptor": {
            "index": 14,
            "url": "/api/proficiencies/14",
            "name": "Chain Mail",
            "desc": []
        }
    },
    {
        "type": "Armor",
        "classes": [],
        "races": [],
        "entry_descriptor": {
            "index": 15,
            "url": "/api/proficiencies/15",
            "name": "Splint",
            "desc": []
        }
    },
    {
        "type": "Armor",
        "classes": [],
        "races": [],
        "entry_descriptor": {
            "index": 16,
            "url": "/api/proficiencies/16",
            "name": "Plate",
            "desc": []
        }
    },
    {
        "type": "Armor",
        "classes": [],
        "races": [],
        "entry_descriptor": {
            "index": 17,
            "url": "/api/proficiencies/17",
            "name": "Shield",
            "desc": []
        }
    },
    {
        "type": "Armor",
        "classes": [
            {
                "url": "/api/classes/1",
                "name": "Barbarian"
            },
            {
                "url": "/api/classes/3",
                "name": "Cleric"
            },
            {
                "url": "/api/classes/4",
                "name": "Druid"
            },
            {
                "url": "/api/classes/5",
                "name": "Fighter"
            },
            {
                "url": "/api/classes/7",
                "name": "Paladin"
            },
            {
                "url": "/api/classes/8",
                "name": "Ranger"
            }
        ],
        "races": [],
        "entry_descriptor": {
            "index": 18,
            "url": "/api/proficiencies/18",
            "name": "Shields",
            "desc": []
        }
    },
    {
        "type": "Weapons",
        "classes": [
            {
                "url": "/api/classes/1",
                "name": "Barbarian"
            },
            {
                "url": "/api/classes/2",
                "name": "Bard"
            },
            {
                "url": "/api/classes/3",
                "name": "Cleric"
            },
            {
                "url": "/api/classes/5",
                "name": "Fighter"
            },
            {
                "url": "/api/classes/6",
                "name": "Monk"
            },
            {
                "url": "/api/classes/7",
                "name": "Paladin"
            },
            {
                "url": "/api/classes/8",
                "name": "Ranger"
            },
            {
                "url": "/api/classes/9",
                "name": "Rogue"
            },
            {
                "url": "/api/classes/11",
                "name": "Warlock"
            }
        ],
        "races": [],
        "entry_descriptor": {
            "index": 19,
            "url": "/api/proficiencies/19",
            "name": "Simple weapons",
            "desc": []
        }
    },
    {
        "type": "Weapons",
        "classes": [
            {
                "url": "/api/classes/1",
                "name": "Barbarian"
            },
            {
                "url": "/api/classes/5",
                "name": "Fighter"
            },
            {
                "url": "/api/classes/7",
                "name": "Paladin"
            },
            {
                "url": "/api/classes/8",
                "name": "Ranger"
            }
        ],
        "races": [],
        "entry_descriptor": {
            "index": 20,
            "url": "/api/proficiencies/20",
            "name": "Martial weapons",
            "desc": []
        }
    },
    {
        "type": "Weapons",
        "classes": [
            {
                "url": "/api/classes/4",
                "name": "Druid"
            }
        ],
        "races": [],
        "entry_descriptor": {
            "index": 21,
            "url": "/api/proficiencies/21",
            "name": "Clubs",
            "desc": []
        }
    },
    {
        "type": "Weapons",
        "classes": [
            {
                "url": "/api/classes/4",
                "name": "Druid"
            },
            {
                "url": "/api/classes/10",
                "name": "Sorcerer"
            },
            {
                "url": "/api/classes/12",
                "name": "Wizard"
            }
        ],
        "races": [],
        "entry_descriptor": {
            "index": 22,
            "url": "/api/proficiencies/22",
            "name": "Daggers",
            "desc": []
        }
    },
    {
        "type": "Weapons",
        "classes": [],
        "races": [],
        "entry_descriptor": {
            "index": 23,
            "url": "/api/proficiencies/23",
            "name": "Greatclubs",
            "desc": []
        }
    },
    {
        "type": "Weapons",
        "classes": [],
        "races": [
            {
                "url": "/api/races/1",
                "name": "Dwarf"
            }
        ],
        "entry_descriptor": {
            "index": 24,
            "url": "/api/proficiencies/24",
            "name": "Handaxes",
            "desc": []
        }
    },
    {
        "type": "Weapons",
        "classes": [
            {
                "url": "/api/classes/4",
                "name": "Druid"
            }
        ],
        "races": [],
        "entry_descriptor": {
            "index": 25,
            "url": "/api/proficiencies/25",
            "name": "Javelins",
            "desc": []
        }
    },
    {
        "type": "Weapons",
        "classes": [],
        "races": [
            {
                "url": "/api/races/1",
                "name": "Dwarf"
            }
        ],
        "entry_descriptor": {
            "index": 26,
            "url": "/api/proficiencies/26",
            "name": "Light hammers",
            "desc": []
        }
    },
    {
        "type": "Weapons",
        "classes": [
            {
                "url": "/api/classes/4",
                "name": "Druid"
            }
        ],
        "races": [],
        "entry_descriptor": {
            "index": 27,
            "url": "/api/proficiencies/27",
            "name": "Maces",
            "desc": []
        }
    },
    {
        "type": "Weapons",
        "classes": [
            {
                "url": "/api/classes/4",
                "name": "Druid"
            },
            {
                "url": "/api/classes/10",
                "name": "Sorcerer"
            },
            {
                "url": "/api/classes/12",
                "name": "Wizard"
            }
        ],
        "races": [],
        "entry_descriptor": {
            "index": 28,
            "url": "/api/proficiencies/28",
            "name": "Quarterstaffs",
            "desc": []
        }
    },
    {
        "type": "Weapons",
        "classes": [
            {
                "url": "/api/classes/4",
                "name": "Druid"
            }
        ],
        "races": [],
        "entry_descriptor": {
            "index": 29,
            "url": "/api/proficiencies/29",
            "name": "Sickles",
            "desc": []
        }
    },
    {
        "type": "Weapons",
        "classes": [
            {
                "url": "/api/classes/4",
                "name": "Druid"
            }
        ],
        "races": [],
        "entry_descriptor": {
            "index": 30,
            "url": "/api/proficiencies/30",
            "name": "Spears",
            "desc": []
        }
    },
    {
        "type": "Weapons",
        "classes": [],
        "races": [],
        "entry_descriptor": {
            "index": 31,
            "url": "/api/proficiencies/31",
            "name": "Crossbows, light",
            "desc": []
        }
    },
    {
        "type": "Weapons",
        "classes": [
            {
                "url": "/api/classes/4",
                "name": "Druid"
            },
            {
                "url": "/api/classes/10",
                "name": "Sorcerer"
            },
            {
                "url": "/api/classes/12",
                "name": "Wizard"
            }
        ],
        "races": [],
        "entry_descriptor": {
            "index": 32,
            "url": "/api/proficiencies/32",
            "name": "Darts",
            "desc": []
        }
    },
    {
        "type": "Weapons",
        "classes": [],
        "races": [
            {
                "url": "/api/subraces/2",
                "name": "High Elf"
            }
        ],
        "entry_descriptor": {
            "index": 33,
            "url": "/api/proficiencies/33",
            "name": "Shortbows",
            "desc": []
        }
    },
    {
        "type": "Weapons",
        "classes": [
            {
                "url": "/api/classes/4",
                "name": "Druid"
            },
            {
                "url": "/api/classes/10",
                "name": "Sorcerer"
            },
            {
                "url": "/api/classes/12",
                "name": "Wizard"
            }
        ],
        "races": [],
        "entry_descriptor": {
            "index": 34,
            "url": "/api/proficiencies/34",
            "name": "Slings",
            "desc": []
        }
    },
    {
        "type": "Weapons",
        "classes": [],
        "races": [
            {
                "url": "/api/races/1",
                "name": "Dwarf"
            }
        ],
        "entry_descriptor": {
            "index": 35,
            "url": "/api/proficiencies/35",
            "name": "Battleaxes",
            "desc": []
        }
    },
    {
        "type": "Weapons",
        "classes": [],
        "races": [],
        "entry_descriptor": {
            "index": 36,
            "url": "/api/proficiencies/36",
            "name": "Flails",
            "desc": []
        }
    },
    {
        "type": "Weapons",
        "classes": [],
        "races": [],
        "entry_descriptor": {
            "index": 37,
            "url": "/api/proficiencies/37",
            "name": "Glaives",
            "desc": []
        }
    },
    {
        "type": "Weapons",
        "classes": [],
        "races": [],
        "entry_descriptor": {
            "index": 38,
            "url": "/api/proficiencies/38",
            "name": "Greataxes",
            "desc": []
        }
    },
    {
        "type": "Weapons",
        "classes": [],
        "races": [],
        "entry_descriptor": {
            "index": 39,
            "url": "/api/proficiencies/39",
            "name": "Greatswords",
            "desc": []
        }
    },
    {
        "type": "Weapons",
        "classes": [],
        "races": [],
        "entry_descriptor": {
            "index": 40,
            "url": "/api/proficiencies/40",
            "name": "Halberds",
            "desc": []
        }
    },
    {
        "type": "Weapons",
        "classes": [],
        "races": [],
        "entry_descriptor": {
            "index": 41,
            "url": "/api/proficiencies/41",
            "name": "Lances",
            "desc": []
        }
    },
    {
        "type": "Weapons",
        "classes": [
            {
                "url": "/api/classes/2",
                "name": "Bard"
            },
            {
                "url": "/api/classes/9",
                "name": "Rogue"
            }
        ],
        "races": [
            {
                "url": "/api/subraces/2",
                "name": "High Elf"
            }
        ],
        "entry_descriptor": {
            "index": 42,
            "url": "/api/proficiencies/42",
            "name": "Longswords",
            "desc": []
        }
    },
    {
        "type": "Weapons",
        "classes": [],
        "races": [],
        "entry_descriptor": {
            "index": 43,
            "url": "/api/proficiencies/43",
            "name": "Mauls",
            "desc": []
        }
    },
    {
        "type": "Weapons",
        "classes": [],
        "races": [],
        "entry_descriptor": {
            "index": 44,
            "url": "/api/proficiencies/44",
            "name": "Morningstars",
            "desc": []
        }
    },
    {
        "type": "Weapons",
        "classes": [],
        "races": [],
        "entry_descriptor": {
            "index": 45,
            "url": "/api/proficiencies/45",
            "name": "Pikes",
            "desc": []
        }
    },
    {
        "type": "Weapons",
        "classes": [
            {
                "url": "/api/classes/2",
                "name": "Bard"
            },
            {
                "url": "/api/classes/9",
                "name": "Rogue"
            }
        ],
        "races": [],
        "entry_descriptor": {
            "index": 46,
            "url": "/api/proficiencies/46",
            "name": "Rapiers",
            "desc": []
        }
    },
    {
        "type": "Weapons",
        "classes": [
            {
                "url": "/api/classes/4",
                "name": "Druid"
            }
        ],
        "races": [],
        "entry_descriptor": {
            "index": 47,
            "url": "/api/proficiencies/47",
            "name": "Scimitars",
            "desc": []
        }
    },
    {
        "type": "Weapons",
        "classes": [
            {
                "url": "/api/classes/2",
                "name": "Bard"
            },
            {
                "url": "/api/classes/6",
                "name": "Monk"
            },
            {
                "url": "/api/classes/9",
                "name": "Rogue"
            }
        ],
        "races": [
            {
                "url": "/api/subraces/2",
                "name": "High Elf"
            }
        ],
        "entry_descriptor": {
            "index": 48,
            "url": "/api/proficiencies/48",
            "name": "Shortswords",
            "desc": []
        }
    },
    {
        "type": "Weapons",
        "classes": [],
        "races": [],
        "entry_descriptor": {
            "index": 49,
            "url": "/api/proficiencies/49",
            "name": "Tridents",
            "desc": []
        }
    },
    {
        "type": "Weapons",
        "classes": [],
        "races": [],
        "entry_descriptor": {
            "index": 50,
            "url": "/api/proficiencies/50",
            "name": "War picks",
            "desc": []
        }
    },
    {
        "type": "Weapons",
        "classes": [],
        "races": [
            {
                "url": "/api/races/1",
                "name": "Dwarf"
            }
        ],
        "entry_descriptor": {
            "index": 51,
            "url": "/api/proficiencies/51",
            "name": "Warhammers",
            "desc": []
        }
    },
    {
        "type": "Weapons",
        "classes": [],
        "races": [],
        "entry_descriptor": {
            "index": 52,
            "url": "/api/proficiencies/52",
            "name": "Whips",
            "desc": []
        }
    },
    {
        "type": "Weapons",
        "classes": [],
        "races": [],
        "entry_descriptor": {
            "index": 53,
            "url": "/api/proficiencies/53",
            "name": "Blowguns",
            "desc": []
        }
    },
    {
        "type": "Weapons",
        "classes": [
            {
                "url": "/api/classes/2",
                "name": "Bard"
            },
            {
                "url": "/api/classes/9",
                "name": "Rogue"
            }
        ],
        "races": [],
        "entry_descriptor": {
            "index": 54,
            "url": "/api/proficiencies/54",
            "name": "Crossbows, hand",
            "desc": []
        }
    },
    {
        "type": "Weapons",
        "classes": [],
        "races": [],
        "entry_descriptor": {
            "index": 55,
            "url": "/api/proficiencies/55",
            "name": "Crossbows, heavy",
            "desc": []
        }
    },
    {
        "type": "Weapons",
        "classes": [],
        "races": [
            {
                "url": "/api/subraces/2",
                "name": "High Elf"
            }
        ],
        "entry_descriptor": {
            "index": 56,
            "url": "/api/proficiencies/56",
            "name": "Longbows",
            "desc": []
        }
    },
    {
        "type": "Weapons",
        "classes": [],
        "races": [],
        "entry_descriptor": {
            "index": 57,
            "url": "/api/proficiencies/57",
            "name": "Nets",
            "desc": []
        }
    },
    {
        "type": "Artisan's Tools",
        "classes": [],
        "races": [],
        "entry_descriptor": {
            "index": 58,
            "url": "/api/proficiencies/58",
            "name": "Alchemist's supplies",
            "desc": []
        }
    },
    {
        "type": "Artisan's Tools",
        "classes": [],
        "races": [],
        "entry_descriptor": {
            "index": 59,
            "url": "/api/proficiencies/59",
            "name": "Brewer's supplies",
            "desc": []
        }
    },
    {
        "type": "Artisan's Tools",
        "classes": [],
        "races": [],
        "entry_descriptor": {
            "index": 60,
            "url": "/api/proficiencies/60",
            "name": "Calligrapher's supplies",
            "desc": []
        }
    },
    {
        "type": "Artisan's Tools",
        "classes": [],
        "races": [],
        "entry_descriptor": {
            "index": 61,
            "url": "/api/proficiencies/61",
            "name": "Carpenter's tools",
            "desc": []
        }
    },
    {
        "type": "Artisan's Tools",
        "classes": [],
        "races": [],
        "entry_descriptor": {
            "index": 62,
            "url": "/api/proficiencies/62",
            "name": "Cartographer's tools",
            "desc": []
        }
    },
    {
        "type": "Artisan's Tools",
        "classes": [],
        "races": [],
        "entry_descriptor": {
            "index": 63,
            "url": "/api/proficiencies/63",
            "name": "Cobbler's tools",
            "desc": []
        }
    },
    {
        "type": "Artisan's Tools",
        "classes": [],
        "races": [],
        "entry_descriptor": {
            "index": 64,
            "url": "/api/proficiencies/64",
            "name": "Cook's utensils",
            "desc": []
        }
    },
    {
        "type": "Artisan's Tools",
        "classes": [],
        "races": [],
        "entry_descriptor": {
            "index": 65,
            "url": "/api/proficiencies/65",
            "name": "Glassblower's tools",
            "desc": []
        }
    },
    {
        "type": "Artisan's Tools",
        "classes": [],
        "races": [],
        "entry_descriptor": {
            "index": 66,
            "url": "/api/proficiencies/66",
            "name": "Jeweler's tools",
            "desc": []
        }
    },
    {
        "type": "Artisan's Tools",
        "classes": [],
        "races": [],
        "entry_descriptor": {
            "index": 67,
            "url": "/api/proficiencies/67",
            "name": "Leatherworker's tools",
            "desc": []
        }
    },
    {
        "type": "Artisan's Tools",
        "classes": [],
        "races": [],
        "entry_descriptor": {
            "index": 68,
            "url": "/api/proficiencies/68",
            "name": "Mason's tools",
            "desc": []
        }
    },
    {
        "type": "Artisan's Tools",
        "classes": [],
        "races": [],
        "entry_descriptor": {
            "index": 69,
            "url": "/api/proficiencies/69",
            "name": "Painter's supplies",
            "desc": []
        }
    },
    {
        "type": "Artisan's Tools",
        "classes": [],
        "races": [],
        "entry_descriptor": {
            "index": 70,
            "url": "/api/proficiencies/70",
            "name": "Potter's tools",
            "desc": []
        }
    },
    {
        "type": "Artisan's Tools",
        "classes": [],
        "races": [],
        "entry_descriptor": {
            "index": 71,
            "url": "/api/proficiencies/71",
            "name": "Smith's tools",
            "desc": []
        }
    },
    {
        "type": "Artisan's Tools",
        "classes": [],
        "races": [],
        "entry_descriptor": {
            "index": 72,
            "url": "/api/proficiencies/72",
            "name": "Tinker's tools",
            "desc": []
        }
    },
    {
        "type": "Artisan's Tools",
        "classes": [],
        "races": [],
        "entry_descriptor": {
            "index": 73,
            "url": "/api/proficiencies/73",
            "name": "Weaver's tools",
            "desc": []
        }
    },
    {
        "type": "Artisan's Tools",
        "classes": [],
        "races": [],
        "entry_descriptor": {
            "index": 74,
            "url": "/api/proficiencies/74",
            "name": "Woodcarver's tools",
            "desc": []
        }
    },
    {
        "type": "Artisan's Tools",
        "classes": [],
        "races": [],
        "entry_descriptor": {
            "index": 75,
            "url": "/api/proficiencies/75",
            "name": "Disguise kit",
            "desc": []
        }
    },
    {
        "type": "Artisan's Tools",
        "classes": [],
        "races": [],
        "entry_descriptor": {
            "index": 76,
            "url": "/api/proficiencies/76",
            "name": "Forgery kit",
            "desc": []
        }
    },
    {
        "type": "Gaming Sets",
        "classes": [],
        "races": [],
        "entry_descriptor": {
            "index": 77,
            "url": "/api/proficiencies/77",
            "name": "Dice Set",
            "desc": []
        }
    },
    {
        "type": "Gaming Sets",
        "classes": [],
        "races": [],
        "entry_descriptor": {
            "index": 78,
            "url": "/api/proficiencies/78",
            "name": "Dragonchess set",
            "desc": []
        }
    },
    {
        "type": "Gaming Sets",
        "classes": [],
        "races": [],
        "entry_descriptor": {
            "index": 79,
            "url": "/api/proficiencies/79",
            "name": "Playing card set",
            "desc": []
        }
    },
    {
        "type": "Gaming Sets",
        "classes": [],
        "races": [],
        "entry_descriptor": {
            "index": 80,
            "url": "/api/proficiencies/80",
            "name": "Three-Dragon Ante set",
            "desc": []
        }
    },
    {
        "type": "Musical Instruments",
        "classes": [],
        "races": [],
        "entry_descriptor": {
            "index": 81,
            "url": "/api/proficiencies/81",
            "name": "Bagpipes",
            "desc": []
        }
    },
    {
        "type": "Musical Instruments",
        "classes": [],
        "races": [],
        "entry_descriptor": {
            "index": 82,
            "url": "/api/proficiencies/82",
            "name": "Drum",
            "desc": []
        }
    },
    {
        "type": "Musical Instruments",
        "classes": [],
        "races": [],
        "entry_descriptor": {
            "index": 83,
            "url": "/api/proficiencies/83",
            "name": "Dulcimer",
            "desc": []
        }
    },
    {
        "type": "Musical Instruments",
        "classes": [],
        "races": [],
        "entry_descriptor": {
            "index": 84,
            "url": "/api/proficiencies/84",
            "name": "Flute",
            "desc": []
        }
    },
    {
        "type": "Musical Instruments",
        "classes": [],
        "races": [],
        "entry_descriptor": {
            "index": 85,
            "url": "/api/proficiencies/85",
            "name": "Lute",
            "desc": []
        }
    },
    {
        "type": "Musical Instruments",
        "classes": [],
        "races": [],
        "entry_descriptor": {
            "index": 86,
            "url": "/api/proficiencies/86",
            "name": "Lyre",
            "desc": []
        }
    },
    {
        "type": "Musical Instruments",
        "classes": [],
        "races": [],
        "entry_descriptor": {
            "index": 87,
            "url": "/api/proficiencies/87",
            "name": "Horn",
            "desc": []
        }
    },
    {
        "type": "Musical Instruments",
        "classes": [],
        "races": [],
        "entry_descriptor": {
            "index": 88,
            "url": "/api/proficiencies/88",
            "name": "Pan flute",
            "desc": []
        }
    },
    {
        "type": "Musical Instruments",
        "classes": [],
        "races": [],
        "entry_descriptor": {
            "index": 89,
            "url": "/api/proficiencies/89",
            "name": "Shawm",
            "desc": []
        }
    },
    {
        "type": "Musical Instruments",
        "classes": [],
        "races": [],
        "entry_descriptor": {
            "index": 90,
            "url": "/api/proficiencies/90",
            "name": "Viol",
            "desc": []
        }
    },
    {
        "type": "Other",
        "classes": [],
        "races": [],
        "entry_descriptor": {
            "index": 91,
            "url": "/api/proficiencies/91",
            "name": "Disguise Kit",
            "desc": []
        }
    },
    {
        "type": "Other",
        "classes": [],
        "races": [],
        "entry_descriptor": {
            "index": 92,
            "url": "/api/proficiencies/92",
            "name": "Forgery Kit",
            "desc": []
        }
    },
    {
        "type": "Other",
        "classes": [
            {
                "url": "/api/classes/4",
                "name": "Druid"
            }
        ],
        "races": [],
        "entry_descriptor": {
            "index": 93,
            "url": "/api/proficiencies/93",
            "name": "Herbalism Kit",
            "desc": []
        }
    },
    {
        "type": "Other",
        "classes": [],
        "races": [],
        "entry_descriptor": {
            "index": 94,
            "url": "/api/proficiencies/94",
            "name": "Navigator's Tools",
            "desc": []
        }
    },
    {
        "type": "Other",
        "classes": [],
        "races": [],
        "entry_descriptor": {
            "index": 95,
            "url": "/api/proficiencies/95",
            "name": "Poisoner's Kit",
            "desc": []
        }
    },
    {
        "type": "Other",
        "classes": [
            {
                "url": "/api/classes/9",
                "name": "Rogue"
            }
        ],
        "races": [],
        "entry_descriptor": {
            "index": 96,
            "url": "/api/proficiencies/96",
            "name": "Thieves' Tools",
            "desc": []
        }
    },
    {
        "type": "Vehicles",
        "classes": [],
        "races": [],
        "entry_descriptor": {
            "index": 97,
            "url": "/api/proficiencies/97",
            "name": "Land Vehicles",
            "desc": []
        }
    },
    {
        "type": "Vehicles",
        "classes": [],
        "races": [],
        "entry_descriptor": {
            "index": 98,
            "url": "/api/proficiencies/98",
            "name": "Water Vehicles",
            "desc": []
        }
    },
    {
        "type": "Saving Throws",
        "classes": [
            {
                "url": "/api/classes/1",
                "name": "Barbarian"
            },
            {
                "url": "/api/classes/5",
                "name": "Fighter"
            },
            {
                "url": "/api/classes/6",
                "name": "Monk"
            },
            {
                "url": "/api/classes/8",
                "name": "Ranger"
            }
        ],
        "races": [],
        "entry_descriptor": {
            "index": 99,
            "url": "/api/proficiencies/99",
            "name": "Saving Throw: STR",
            "desc": []
        }
    },
    {
        "type": "Saving Throws",
        "classes": [
            {
                "url": "/api/classes/2",
                "name": "Bard"
            },
            {
                "url": "/api/classes/6",
                "name": "Monk"
            },
            {
                "url": "/api/classes/8",
                "name": "Ranger"
            },
            {
                "url": "/api/classes/9",
                "name": "Rogue"
            }
        ],
        "races": [],
        "entry_descriptor": {
            "index": 100,
            "url": "/api/proficiencies/100",
            "name": "Saving Throw: DEX",
            "desc": []
        }
    },
    {
        "type": "Saving Throws",
        "classes": [
            {
                "url": "/api/classes/1",
                "name": "Barbarian"
            },
            {
                "url": "/api/classes/5",
                "name": "Fighter"
            },
            {
                "url": "/api/classes/10",
                "name": "Sorcerer"
            }
        ],
        "races": [],
        "entry_descriptor": {
            "index": 101,
            "url": "/api/proficiencies/101",
            "name": "Saving Throw: CON",
            "desc": []
        }
    },
    {
        "type": "Saving Throws",
        "classes": [
            {
                "url": "/api/classes/4",
                "name": "Druid"
            },
            {
                "url": "/api/classes/9",
                "name": "Rogue"
            },
            {
                "url": "/api/classes/12",
                "name": "Wizard"
            }
        ],
        "races": [],
        "entry_descriptor": {
            "index": 102,
            "url": "/api/proficiencies/102",
            "name": "Saving Throw: INT",
            "desc": []
        }
    },
    {
        "type": "Saving Throws",
        "classes": [
            {
                "url": "/api/classes/3",
                "name": "Cleric"
            },
            {
                "url": "/api/classes/4",
                "name": "Druid"
            },
            {
                "url": "/api/classes/7",
                "name": "Paladin"
            },
            {
                "url": "/api/classes/11",
                "name": "Warlock"
            },
            {
                "url": "/api/classes/12",
                "name": "Wizard"
            }
        ],
        "races": [],
        "entry_descriptor": {
            "index": 103,
            "url": "/api/proficiencies/103",
            "name": "Saving Throw: WIS",
            "desc": []
        }
    },
    {
        "type": "Saving Throws",
        "classes": [
            {
                "url": "/api/classes/2",
                "name": "Bard"
            },
            {
                "url": "/api/classes/3",
                "name": "Cleric"
            },
            {
                "url": "/api/classes/7",
                "name": "Paladin"
            },
            {
                "url": "/api/classes/10",
                "name": "Sorcerer"
            },
            {
                "url": "/api/classes/11",
                "name": "Warlock"
            }
        ],
        "races": [],
        "entry_descriptor": {
            "index": 104,
            "url": "/api/proficiencies/104",
            "name": "Saving Throw: CHA",
            "desc": []
        }
    },
    {
        "type": "Skills",
        "classes": [],
        "races": [],
        "entry_descriptor": {
            "index": 105,
            "url": "/api/proficiencies/105",
            "name": "Skill: Acrobatics",
            "desc": []
        }
    },
    {
        "type": "Skills",
        "classes": [],
        "races": [],
        "entry_descriptor": {
            "index": 106,
            "url": "/api/proficiencies/106",
            "name": "Skill: Animal Handling",
            "desc": []
        }
    },
    {
        "type": "Skills",
        "classes": [],
        "races": [],
        "entry_descriptor": {
            "index": 107,
            "url": "/api/proficiencies/107",
            "name": "Skill: Arcana",
            "desc": []
        }
    },
    {
        "type": "Skills",
        "classes": [],
        "races": [],
        "entry_descriptor": {
            "index": 108,
            "url": "/api/proficiencies/108",
            "name": "Skill: Athletics",
            "desc": []
        }
    },
    {
        "type": "Skills",
        "classes": [],
        "races": [],
        "entry_descriptor": {
            "index": 109,
            "url": "/api/proficiencies/109",
            "name": "Skill: Deception",
            "desc": []
        }
    },
    {
        "type": "Skills",
        "classes": [],
        "races": [],
        "entry_descriptor": {
            "index": 110,
            "url": "/api/proficiencies/110",
            "name": "Skill: History",
            "desc": []
        }
    },
    {
        "type": "Skills",
        "classes": [],
        "races": [],
        "entry_descriptor": {
            "index": 111,
            "url": "/api/proficiencies/111",
            "name": "Skill: Insight",
            "desc": []
        }
    },
    {
        "type": "Skills",
        "classes": [],
        "races": [],
        "entry_descriptor": {
            "index": 112,
            "url": "/api/proficiencies/112",
            "name": "Skill: Intimidation",
            "desc": []
        }
    },
    {
        "type": "Skills",
        "classes": [],
        "races": [],
        "entry_descriptor": {
            "index": 113,
            "url": "/api/proficiencies/113",
            "name": "Skill: Investigation",
            "desc": []
        }
    },
    {
        "type": "Skills",
        "classes": [],
        "races": [],
        "entry_descriptor": {
            "index": 114,
            "url": "/api/proficiencies/114",
            "name": "Skill: Medicine",
            "desc": []
        }
    },
    {
        "type": "Skills",
        "classes": [],
        "races": [],
        "entry_descriptor": {
            "index": 115,
            "url": "/api/proficiencies/115",
            "name": "Skill: Nature",
            "desc": []
        }
    },
    {
        "type": "Skills",
        "classes": [],
        "races": [
            {
                "url": "/api/races/2",
                "name": "Elf"
            }
        ],
        "entry_descriptor": {
            "index": 116,
            "url": "/api/proficiencies/116",
            "name": "Skill: Perception",
            "desc": []
        }
    },
    {
        "type": "Skills",
        "classes": [],
        "races": [],
        "entry_descriptor": {
            "index": 117,
            "url": "/api/proficiencies/117",
            "name": "Skill: Performance",
            "desc": []
        }
    },
    {
        "type": "Skills",
        "classes": [],
        "races": [],
        "entry_descriptor": {
            "index": 118,
            "url": "/api/proficiencies/118",
            "name": "Skill: Persuasion",
            "desc": []
        }
    },
    {
        "type": "Skills",
        "classes": [],
        "races": [],
        "entry_descriptor": {
            "index": 119,
            "url": "/api/proficiencies/119",
            "name": "Skill: Religion",
            "desc": []
        }
    },
    {
        "type": "Skills",
        "classes": [],
        "races": [],
        "entry_descriptor": {
            "index": 120,
            "url": "/api/proficiencies/120",
            "name": "Skill: Sleight of Hand",
            "desc": []
        }
    },
    {
        "type": "Skills",
        "classes": [],
        "races": [],
        "entry_descriptor": {
            "index": 121,
            "url": "/api/proficiencies/121",
            "name": "Skill: Stealth",
            "desc": []
        }
    },
    {
        "type": "Skills",
        "classes": [],
        "races": [],
        "entry_descriptor": {
            "index": 122,
            "url": "/api/proficiencies/122",
            "name": "Skill: Survival",
            "desc": []
        }
    }
]